pushover_complete/__init__.py
pushover_complete/error.py
pushover_complete/pushover_api.py
pushover_complete-1.1.1.dist-info/METADATA
pushover_complete-1.1.1.dist-info/RECORD
pushover_complete-1.1.1.dist-info/WHEEL
pushover_complete-1.1.1.dist-info/top_level.txt
