Metadata-Version: 1.2
Name: pushover-complete
Version: 1.1.1
Summary: A Python package for interacting with *all* aspects of the Pushover API
Home-page: https://github.com/scolby33/pushover_complete
Author: Scott Colby
Author-email: scolby33@gmail.com
Maintainer: Scott Colby
License: MIT License
Keywords: pushover,message,push
Platform: UNKNOWN
Classifier: Development Status :: 5 - Production/Stable
Classifier: Intended Audience :: Developers
Classifier: License :: OSI Approved :: MIT License
Classifier: Operating System :: OS Independent
Classifier: Programming Language :: Python
Classifier: Programming Language :: Python :: 2.7
Classifier: Programming Language :: Python :: 3.5
Classifier: Programming Language :: Python :: 3.6
Classifier: Topic :: Communications
